galmask/__init__.py
galmask/galmask.py
galmask/utils.py
tests/__init__.py
tests/test_galmask.py
tests/test_utils.py
galmask-0.2.0.dist-info/LICENSE
galmask-0.2.0.dist-info/METADATA
galmask-0.2.0.dist-info/WHEEL
galmask-0.2.0.dist-info/top_level.txt
galmask-0.2.0.dist-info/RECORD
