Metadata-Version: 2.1
Name: galmask
Version: 0.2.0
Summary: "Unsupervised galaxy masking to remove background source detections"
Home-page: https://github.com/Yash-10/galmask
License: MIT
Classifier: Programming Language :: Python :: 3
Classifier: License :: OSI Approved :: MIT License
Requires-Python: >=3.8
License-File: LICENSE
Requires-Dist: numpy (>=1.18)
Requires-Dist: astropy (>=5.0)
Requires-Dist: photutils (>=1.4.0)
Requires-Dist: scikit-image (>=0.15.0)
Requires-Dist: opencv-python (<4.5.5.62,>=4.5.4.0)
Requires-Dist: scipy (>=1.6.0)
